cdk_codepipeline_badge_notification/__init__.py
cdk_codepipeline_badge_notification/py.typed
cdk_codepipeline_badge_notification/_jsii/__init__.py
cdk_codepipeline_badge_notification/_jsii/cdk-codepipeline-badge-notification@2.0.78.jsii.tgz
cdk_codepipeline_badge_notification-2.0.78.dist-info/LICENSE
cdk_codepipeline_badge_notification-2.0.78.dist-info/METADATA
cdk_codepipeline_badge_notification-2.0.78.dist-info/WHEEL
cdk_codepipeline_badge_notification-2.0.78.dist-info/top_level.txt
cdk_codepipeline_badge_notification-2.0.78.dist-info/RECORD
