Metadata-Version: 2.1
Name: cdk-codepipeline-badge-notification
Version: 2.0.78
Summary: cdk-codepipeline-badge-notification
Home-page: https://github.com/kimisme9386/cdk-codepipeline-badge-notification
Author: Chris Yang
License: Apache-2.0
Project-URL: Source, https://github.com/kimisme9386/cdk-codepipeline-badge-notification
Platform: UNKNOWN
Classifier: Intended Audience :: Developers
Classifier: Operating System :: OS Independent
Classifier: Programming Language :: JavaScript
Classifier: Programming Language :: Python :: 3 :: Only
Classifier: Programming Language :: Python :: 3.6
Classifier: Programming Language :: Python :: 3.7
Classifier: Programming Language :: Python :: 3.8
Classifier: Programming Language :: Python :: 3.9
Classifier: Typing :: Typed
Classifier: Development Status :: 4 - Beta
Classifier: License :: OSI Approved
Requires-Python: >=3.6
License-File: LICENSE
Requires-Dist: aws-cdk-lib (<3.0.0,>=2.1.0)
Requires-Dist: constructs (<11.0.0,>=10.0.5)
Requires-Dist: jsii (<2.0.0,>=1.55.1)
Requires-Dist: publication (>=0.0.3)
